elg/__init__.py
elg/authentication.py
elg/benchmark.py
elg/catalog.py
elg/corpus.py
elg/entity.py
elg/flask_service.py
elg/local_installation.py
elg/pipeline.py
elg/provider.py
elg/quart_service.py
elg/service.py
elg/cli/__init__.py
elg/cli/docker.py
elg/cli/docker_create.py
elg/cli/download.py
elg/cli/elg.py
elg/cli/info.py
elg/cli/local_installation.py
elg/cli/local_installation_docker.py
elg/cli/local_installation_ids.py
elg/cli/run.py
elg/cli/search.py
elg/model/__init__.py
elg/model/base/Annotation.py
elg/model/base/Failure.py
elg/model/base/Progress.py
elg/model/base/Request.py
elg/model/base/ResponseObject.py
elg/model/base/StandardMessages.py
elg/model/base/StatusMessage.py
elg/model/base/__init__.py
elg/model/base/utils.py
elg/model/request/AudioRequest.py
elg/model/request/ImageRequest.py
elg/model/request/StructuredTextRequest.py
elg/model/request/TextRequest.py
elg/model/request/__init__.py
elg/model/response/AnnotationsResponse.py
elg/model/response/AudioResponse.py
elg/model/response/ClassificationResponse.py
elg/model/response/TextsResponse.py
elg/model/response/__init__.py
elg/model/response/utils.py
elg/utils/ISO639.py
elg/utils/MIME.py
elg/utils/__init__.py
elg/utils/_generate_standard_messages.py
elg/utils/docker.py
elg/utils/errors.py
elg/utils/json_encoder.py
elg/utils/local_installation.py
elg/utils/utils.py
elg-0.6.0.dist-info/LICENSE
elg-0.6.0.dist-info/METADATA
elg-0.6.0.dist-info/WHEEL
elg-0.6.0.dist-info/entry_points.txt
elg-0.6.0.dist-info/top_level.txt
elg-0.6.0.dist-info/RECORD
