Metadata-Version: 2.1
Name: elg
Version: 0.6.0
Summary: Use the European Language Grid in your Python projects
Home-page: https://gitlab.com/european-language-grid/platform/python-client
Author: ELG Technical Team
Author-email: contact@european-language-grid.eu
License: MIT
Keywords: tools,sdk,language technology,europe,european,nlp
Classifier: Development Status :: 3 - Alpha
Classifier: Intended Audience :: Developers
Classifier: Intended Audience :: Education
Classifier: Intended Audience :: Science/Research
Classifier: License :: OSI Approved :: MIT License
Classifier: Operating System :: OS Independent
Classifier: Programming Language :: Python :: 3
Classifier: Programming Language :: Python :: 3.6
Classifier: Programming Language :: Python :: 3.7
Classifier: Programming Language :: Python :: 3.8
Classifier: Programming Language :: Python :: 3.9
Classifier: Programming Language :: Python :: 3.10
Classifier: Programming Language :: Python :: 3.11
Classifier: Topic :: Scientific/Engineering :: Artificial Intelligence
Requires-Python: >=3.6.0
License-File: LICENSE
Requires-Dist: requests>=2.25
Requires-Dist: tqdm>=4.49
Requires-Dist: pandas>=1.2
Requires-Dist: loguru>=0.5
Requires-Dist: pydantic<3,>=1.7.4
Provides-Extra: flask
Requires-Dist: flask>=2.2; extra == "flask"
Requires-Dist: docker>=5.0; extra == "flask"
Requires-Dist: requests_toolbelt>=0.9; extra == "flask"
Provides-Extra: quart
Requires-Dist: quart>=0.18.0; extra == "quart"
Requires-Dist: docker>=5.0; extra == "quart"
Requires-Dist: requests_toolbelt>=0.9; extra == "quart"
Provides-Extra: quality
Requires-Dist: black==23.3.0; extra == "quality"
Requires-Dist: isort==5.12.0; extra == "quality"
